{
    "original": "MÅNSSON, Alfred Victor, Civilingenjör, Malmö, f Ask, Malmöh l, 1/7 91 av nmdem Måns Andersson o Emilia Andersson, gm Thérese Arwidsson. Studex Lund 10, CTH (VoV) 16. Anst: William Fagerström Gbg 16, örlogsvarvet (byggn.dep) Sth 16, AB Nordströms linbanor Sthlm 17, John Lindbergs ing.byrå Gbg 18—19, Södra Gorns varv 19, Haij s ing.-byrå Gbg 20, sed. 20 eg konsult ingbyrå i byggn.bransch o väg- o vatt m spec fabr- o ind.byggn. Styr.led Sk ing.klb, S Sv Byggn.-tekn samf. Resor: Tyskl 21, Tyskl, Lettl 33, Tyskl, Österr, Ung, Tjeckoslov 36, Holl 38, Engl 34. Av trycket »Beräkn av betongsekt m styv armering» Byggn.tidn 22, »Om dränering» Handb f kyrkogårdsvård, utg av Else Dahl. Odd Fellow, Par Bricole, Sällsk Heimdall, KAK, Tekn Samf, Frn Tekn Muséet, Kult.hist frn f S Sv, Malmö ind.frn, Astron Sällsk Tycho Brahe mfl. Hobby: Musik.",
    "translated": "MÅNSSON, Alfred Victor, Civil Engineer, Malmö, born in Ask, Malmöhus County, on July 1, 1891, to parents Måns Andersson and Emilia Andersson, married to Thérese Arwidsson. Completed studies in Lund 1910, Royal Institute of Technology (VoV) 1916. Employment: William Fagerström, Gothenburg 1916, Naval Shipyard (Construction Department), Stockholm 1916, AB Nordström's suspension railways, Stockholm 1917, John Lindberg's engineering office, Gothenburg 1918-1919, Södra Gorns shipyard 1919, Haij's engineering office, Gothenburg 1920, self-employed consultant in the construction industry and road and water management with specialist factory and industrial buildings since 1920. Board member of the Swedish Engineering Club, Swedish Building Technology Association. Travel history: Germany 1921, Germany and Latvia 1933, Germany, Austria, Hungary, Czechoslovakia 1936, the Netherlands 1938, England 1934. Published works: \"Concrete Calculation with Rigid Reinforcement\" in Byggnadstidningen 1922, \"About Drainage\" in the Handbook of Cemetery Maintenance published by Else Dahl. Member of Odd Fellow, Par Bricole, Society Heimdall, KAK, Engineering Society, From the Technical Museum, Cultural history from the South Swedish Association, Malmö Industrial Association, Astronomical Society Tycho Brahe, among others. Hobby: Music.",
    "structured": {
        "@context": "https://schema.org",
        "@type": "Person",
        "name": "Alfred Victor Månsson",
        "birthDate": "1891-07-01",
        "birthPlace": "Ask, Malmöhus County, Sweden",
        "nationality": "Swedish",
        "jobTitle": "Civil Engineer",
        "memberOf": [
            {
                "@type": "Organization",
                "name": "Odd Fellow"
            },
            {
                "@type": "Organization",
                "name": "Par Bricole"
            },
            {
                "@type": "Organization",
                "name": "Society Heimdall"
            },
            {
                "@type": "Organization",
                "name": "KAK"
            },
            {
                "@type": "Organization",
                "name": "Swedish Engineering Club"
            },
            {
                "@type": "Organization",
                "name": "Swedish Building Technology Association"
            },
            {
                "@type": "Organization",
                "name": "Technical Museum"
            },
            {
                "@type": "Organization",
                "name": "South Swedish Association"
            },
            {
                "@type": "Organization",
                "name": "Malmö Industrial Association"
            },
            {
                "@type": "Organization",
                "name": "Astronomical Society Tycho Brahe"
            }
        ],
        "spouse": {
            "@type": "Person",
            "name": "Thérese Arwidsson"
        },
        "education": [
            {
                "@type": "EducationalOccupationalCredential",
                "credentialCategory": "Diploma",
                "educationalLevel": "Bachelors",
                "awardedBy": {
                    "@type": "CollegeOrUniversity",
                    "name": "Lund University"
                },
                "yearCredentialAwarded": "1910"
            },
            {
                "@type": "EducationalOccupationalCredential",
                "credentialCategory": "Diploma",
                "educationalLevel": "Masters",
                "awardedBy": {
                    "@type": "CollegeOrUniversity",
                    "name": "Royal Institute of Technology"
                },
                "yearCredentialAwarded": "1916"
            }
        ],
        "work": [
            {
                "@type": "Organization",
                "name": "William Fagerström",
                "startDate": "1916-01-01",
                "endDate": "1916-12-31",
                "location": "Gothenburg"
            },
            {
                "@type": "Organization",
                "name": "Naval Shipyard",
                "department": "Construction Department",
                "startDate": "1916-01-01",
                "endDate": "1916-12-31",
                "location": "Stockholm"
            },
            {
                "@type": "Organization",
                "name": "AB Nordström's suspension railways",
                "startDate": "1917-01-01",
                "endDate": "1917-12-31",
                "location": "Stockholm"
            },
            {
                "@type": "Organization",
                "name": "John Lindberg's engineering office",
                "startDate": "1918-01-01",
                "endDate": "1919-12-31",
                "location": "Gothenburg"
            },
            {
                "@type": "Organization",
                "name": "Södra Gorns shipyard",
                "startDate": "1919-01-01",
                "endDate": "1919-12-31"
            },
            {
                "@type": "Organization",
                "name": "Haij's engineering office",
                "startDate": "1920-01-01",
                "location": "Gothenburg"
            },
            {
                "@type": "Organization",
                "name": "Self-employed",
                "description": "Consultant in the construction industry and road and water management with specialist factory and industrial buildings",
                "startDate": "1920-01-01"
            }
        ],
        "publication": [
            {
                "@type": "Article",
                "headline": "Concrete Calculation with Rigid Reinforcement",
                "publicationDate": "1922-01-01",
                "publisher": {
                    "@type": "Periodical",
                    "name": "Byggnadstidningen"
                }
            },
            {
                "@type": "Article",
                "headline": "About Drainage",
                "publicationDate": "unknown",
                "publisher": {
                    "@type": "Book",
                    "name": "Handbook of Cemetery Maintenance",
                    "author": "Else Dahl"
                }
            }
        ],
        "travelHistory": [
            {
                "@type": "Place",
                "name": "Germany",
                "travelDate": "1921"
            },
            {
                "@type": "Place",
                "name": "Germany",
                "travelDate": "1933"
            },
            {
                "@type": "Place",
                "name": "Latvia",
                "travelDate": "1933"
            },
            {
                "@type": "Place",
                "name": "Germany",
                "travelDate": "1936"
            },
            {
                "@type": "Place",
                "name": "Austria",
                "travelDate": "1936"
            },
            {
                "@type": "Place",
                "name": "Hungary",
                "travelDate": "1936"
            },
            {
                "@type": "Place",
                "name": "Czechoslovakia",
                "travelDate": "1936"
            },
            {
                "@type": "Place",
                "name": "Netherlands",
                "travelDate": "1938"
            },
            {
                "@type": "Place",
                "name": "England",
                "travelDate": "1934"
            }
        ],
        "hobby": "Music"
    },
    "occupations": {
        "career": [
            {
                "occupational_title": "Civil Engineer",
                "workplace": "William Fagerström",
                "industry": "Construction",
                "start_date": "1916"
            },
            {
                "occupational_title": "Construction Department",
                "workplace": "Naval Shipyard",
                "industry": "Construction",
                "start_date": "1916"
            },
            {
                "occupational_title": "Suspension Railways",
                "workplace": "AB Nordström",
                "industry": "Transportation",
                "start_date": "1917"
            },
            {
                "occupational_title": "Engineering Office",
                "workplace": "John Lindbergs",
                "industry": "Engineering",
                "start_date": "1918"
            },
            {
                "occupational_title": "Shipyard",
                "workplace": "Södra Gorns",
                "industry": "Maritime",
                "start_date": "1919"
            },
            {
                "occupational_title": "Engineering Office",
                "workplace": "Haij's",
                "industry": "Engineering",
                "start_date": "1920"
            },
            {
                "occupational_title": "Self-employed Consultant",
                "workplace": " - ",
                "industry": "Construction",
                "start_date": "1920"
            }
        ]
    }
}