{
    "original": "HERDER, Folke Gunnar, Försäljningschef, Borås, f Borås 26/8 09 av lagerchef M H o Hilda Håkansson, gm Alice Svedberg. Realex 25. Anst 25 som elev i dåv fma W:m Rudell, Borås, sederm ombild t W:m Rudell AB, inköps- o försäljn.ch där efter 9 års praktik i färg o kemik.branschen. Ag fastigh Gustav Adolfsgat 63, Borås. Par Bricole. Hobby: Skytte.",
    "translated": "HERDER, Folke Gunnar, Sales Manager, Borås, born in Borås on August 26, 1909, to warehouse manager M H and Hilda Håkansson, married to Alice Svedberg. Finished primary school at the age of 25. Started working as a trainee at the then-established W:m Rudell, Borås, and later became a purchasing and sales director at W:m Rudell AB after 9 years of practical experience in the paint and chemical industry. Owns a property at Gustav Adolfsgat 63, Borås. Married to Bricole. Hobby: Shooting.",
    "structured": {
        "name": "Folke Gunnar Herder",
        "jobTitle": "Sales Manager",
        "birthDate": "1909-08-26",
        "birthPlace": "Borås, Sweden",
        "father": {
            "name": "M H Håkansson",
            "jobTitle": "Warehouse Manager"
        },
        "mother": {
            "name": "Hilda Håkansson"
        },
        "spouse": {
            "name": "Alice Svedberg"
        },
        "education": {
            "startDate": "1934",
            "endDate": "1934",
            "description": "Primary school"
        },
        "work": [
            {
                "startDate": "1934",
                "endDate": "1943",
                "employer": "W:m Rudell",
                "title": "Trainee",
                "description": "W:m Rudell, Borås"
            },
            {
                "startDate": "1943",
                "employer": "W:m Rudell AB",
                "title": "Purchasing and Sales Director",
                "description": "Paint and Chemical Industry"
            }
        ],
        "address": {
            "streetAddress": "Gustav Adolfsgat 63",
            "addressLocality": "Borås",
            "addressCountry": "Sweden"
        },
        "maritalStatus": "Married",
        "spouseName": "Bricole",
        "hobby": "Shooting"
    },
    "occupations": {
        "career": [
            {
                "occupational_title": "Trainee",
                "workplace": "W:m Rudell, Borås",
                "industry": "Paint and chemical",
                "start_date": "1934"
            },
            {
                "occupational_title": "Purchasing and Sales Director",
                "workplace": "W:m Rudell AB",
                "industry": "Paint and chemical",
                "start_date": "1943"
            },
            {
                "occupational_title": "Sales Manager",
                "workplace": "Borås",
                "industry": "Not specified",
                "start_date": "Not specified"
            }
        ]
    }
}